{"note":"This file is an internal implementation detail to speed up HTML report generation. Its format can change at any time. You might be looking for the JSON report: https://coverage.rtfd.io/cmd.html#cmd-json","format":5,"version":"7.13.1","globals":"8326daea03c2a5ceeb050788ed75b6f1","files":{"z_15eb941870a4f5f1_admin_py":{"hash":"49e423418b75322a5e135fcb459c72b5","index":{"url":"z_15eb941870a4f5f1_admin_py.html","file":"account/admin.py","description":"","nums":{"precision":2,"n_files":1,"n_statements":6,"n_excluded":0,"n_missing":0,"n_branches":0,"n_partial_branches":0,"n_missing_branches":0}}},"z_15eb941870a4f5f1_apps_py":{"hash":"4f03116f8bc39f685884611f35b9aa50","index":{"url":"z_15eb941870a4f5f1_apps_py.html","file":"account/apps.py","description":"","nums":{"precision":2,"n_files":1,"n_statements":4,"n_excluded":0,"n_missing":0,"n_branches":0,"n_partial_branches":0,"n_missing_branches":0}}},"z_15eb941870a4f5f1_authentication_py":{"hash":"f2476e8a5342a9b4b93aee677069d130","index":{"url":"z_15eb941870a4f5f1_authentication_py.html","file":"account/authentication.py","description":"","nums":{"precision":2,"n_files":1,"n_statements":18,"n_excluded":0,"n_missing":18,"n_branches":2,"n_partial_branches":0,"n_missing_branches":2}}},"z_15eb941870a4f5f1_forms_py":{"hash":"4eff07ca20a375217c4371350448bf42","index":{"url":"z_15eb941870a4f5f1_forms_py.html","file":"account/forms.py","description":"","nums":{"precision":2,"n_files":1,"n_statements":36,"n_excluded":0,"n_missing":36,"n_branches":6,"n_partial_branches":0,"n_missing_branches":6}}},"z_15eb941870a4f5f1_models_py":{"hash":"80d116020fc6f9b41fda306b9fa2a9e3","index":{"url":"z_15eb941870a4f5f1_models_py.html","file":"account/models.py","description":"","nums":{"precision":2,"n_files":1,"n_statements":20,"n_excluded":0,"n_missing":2,"n_branches":0,"n_partial_branches":0,"n_missing_branches":0}}},"z_36c34a06426a17e7_test_forms_py":{"hash":"a89cf3ae72f0413618c30efc54078bfe","index":{"url":"z_36c34a06426a17e7_test_forms_py.html","file":"account/tests/test_forms.py","description":"","nums":{"precision":2,"n_files":1,"n_statements":2,"n_excluded":0,"n_missing":0,"n_branches":0,"n_partial_branches":0,"n_missing_branches":0}}},"z_36c34a06426a17e7_test_models_py":{"hash":"a89cf3ae72f0413618c30efc54078bfe","index":{"url":"z_36c34a06426a17e7_test_models_py.html","file":"account/tests/test_models.py","description":"","nums":{"precision":2,"n_files":1,"n_statements":2,"n_excluded":0,"n_missing":0,"n_branches":0,"n_partial_branches":0,"n_missing_branches":0}}},"z_36c34a06426a17e7_test_urls_py":{"hash":"a89cf3ae72f0413618c30efc54078bfe","index":{"url":"z_36c34a06426a17e7_test_urls_py.html","file":"account/tests/test_urls.py","description":"","nums":{"precision":2,"n_files":1,"n_statements":2,"n_excluded":0,"n_missing":0,"n_branches":0,"n_partial_branches":0,"n_missing_branches":0}}},"z_36c34a06426a17e7_test_views_py":{"hash":"a89cf3ae72f0413618c30efc54078bfe","index":{"url":"z_36c34a06426a17e7_test_views_py.html","file":"account/tests/test_views.py","description":"","nums":{"precision":2,"n_files":1,"n_statements":2,"n_excluded":0,"n_missing":0,"n_branches":0,"n_partial_branches":0,"n_missing_branches":0}}},"z_15eb941870a4f5f1_urls_py":{"hash":"cef8aead225c29a7a932830c7454db01","index":{"url":"z_15eb941870a4f5f1_urls_py.html","file":"account/urls.py","description":"","nums":{"precision":2,"n_files":1,"n_statements":3,"n_excluded":0,"n_missing":3,"n_branches":0,"n_partial_branches":0,"n_missing_branches":0}}},"z_15eb941870a4f5f1_views_py":{"hash":"01066b9f2410e4067a1c6d45147e37eb","index":{"url":"z_15eb941870a4f5f1_views_py.html","file":"account/views.py","description":"","nums":{"precision":2,"n_files":1,"n_statements":82,"n_excluded":0,"n_missing":82,"n_branches":22,"n_partial_branches":0,"n_missing_branches":22}}},"z_051dcf22948e5c16_admin_py":{"hash":"9d67843a07c3cce5b72837b46ae81bb5","index":{"url":"z_051dcf22948e5c16_admin_py.html","file":"actions/admin.py","description":"","nums":{"precision":2,"n_files":1,"n_statements":7,"n_excluded":0,"n_missing":0,"n_branches":0,"n_partial_branches":0,"n_missing_branches":0}}},"z_051dcf22948e5c16_apps_py":{"hash":"861cdbabe280fcc9e24091de48b6f8bf","index":{"url":"z_051dcf22948e5c16_apps_py.html","file":"actions/apps.py","description":"","nums":{"precision":2,"n_files":1,"n_statements":4,"n_excluded":0,"n_missing":0,"n_branches":0,"n_partial_branches":0,"n_missing_branches":0}}},"z_051dcf22948e5c16_models_py":{"hash":"ed92bde0a0345021de33f3eaf0680a0a","index":{"url":"z_051dcf22948e5c16_models_py.html","file":"actions/models.py","description":"","nums":{"precision":2,"n_files":1,"n_statements":15,"n_excluded":0,"n_missing":1,"n_branches":0,"n_partial_branches":0,"n_missing_branches":0}}},"z_b8c767d1f0d3f985_test_forms_py":{"hash":"a89cf3ae72f0413618c30efc54078bfe","index":{"url":"z_b8c767d1f0d3f985_test_forms_py.html","file":"actions/tests/test_forms.py","description":"","nums":{"precision":2,"n_files":1,"n_statements":2,"n_excluded":0,"n_missing":0,"n_branches":0,"n_partial_branches":0,"n_missing_branches":0}}},"z_b8c767d1f0d3f985_test_models_py":{"hash":"a89cf3ae72f0413618c30efc54078bfe","index":{"url":"z_b8c767d1f0d3f985_test_models_py.html","file":"actions/tests/test_models.py","description":"","nums":{"precision":2,"n_files":1,"n_statements":2,"n_excluded":0,"n_missing":0,"n_branches":0,"n_partial_branches":0,"n_missing_branches":0}}},"z_b8c767d1f0d3f985_test_urls_py":{"hash":"a89cf3ae72f0413618c30efc54078bfe","index":{"url":"z_b8c767d1f0d3f985_test_urls_py.html","file":"actions/tests/test_urls.py","description":"","nums":{"precision":2,"n_files":1,"n_statements":2,"n_excluded":0,"n_missing":0,"n_branches":0,"n_partial_branches":0,"n_missing_branches":0}}},"z_b8c767d1f0d3f985_test_views_py":{"hash":"a89cf3ae72f0413618c30efc54078bfe","index":{"url":"z_b8c767d1f0d3f985_test_views_py.html","file":"actions/tests/test_views.py","description":"","nums":{"precision":2,"n_files":1,"n_statements":2,"n_excluded":0,"n_missing":0,"n_branches":0,"n_partial_branches":0,"n_missing_branches":0}}},"z_051dcf22948e5c16_utils_py":{"hash":"21c1df8c29e85901a364624989444181","index":{"url":"z_051dcf22948e5c16_utils_py.html","file":"actions/utils.py","description":"","nums":{"precision":2,"n_files":1,"n_statements":16,"n_excluded":0,"n_missing":16,"n_branches":4,"n_partial_branches":0,"n_missing_branches":4}}},"z_051dcf22948e5c16_views_py":{"hash":"d6629ccb535725e0c94130e3a7400a91","index":{"url":"z_051dcf22948e5c16_views_py.html","file":"actions/views.py","description":"","nums":{"precision":2,"n_files":1,"n_statements":0,"n_excluded":0,"n_missing":0,"n_branches":0,"n_partial_branches":0,"n_missing_branches":0}}},"z_1ea838694151cac8_test_py":{"hash":"dbffdd703e08a4f71398b598270c1693","index":{"url":"z_1ea838694151cac8_test_py.html","file":"config/test.py","description":"","nums":{"precision":2,"n_files":1,"n_statements":5,"n_excluded":0,"n_missing":0,"n_branches":0,"n_partial_branches":0,"n_missing_branches":0}}},"z_1ea838694151cac8_urls_py":{"hash":"1b09ea1d99a8168dc094dc5733992b38","index":{"url":"z_1ea838694151cac8_urls_py.html","file":"config/urls.py","description":"","nums":{"precision":2,"n_files":1,"n_statements":6,"n_excluded":2,"n_missing":6,"n_branches":0,"n_partial_branches":0,"n_missing_branches":0}}}}}